create_app/__init__.py
create_app/__main__.py
create_app/cli.py
create_app/main.py
create_app/project.py
create_app/project_configuration.py
create_app/project_configuration_file.py
create_app/settings.py
create_app/templates.py
create_app-0.6.2.dist-info/LICENSE
create_app-0.6.2.dist-info/METADATA
create_app-0.6.2.dist-info/WHEEL
create_app-0.6.2.dist-info/entry_points.txt
create_app-0.6.2.dist-info/top_level.txt
create_app-0.6.2.dist-info/RECORD
